[
  {
    "intent": "learned.1773046646084",
    "utterance": "Mokut na oy mk",
    "response": "මුකුත්  නැ පැටියෝ..💖🔓\nඔයා මොකද කරන්නෙ..💓🌷"
  },
  {
    "intent": "learned.1773049613590",
    "utterance": "Huu kiynne ai",
    "response": "Huh"
  },
  {
    "intent": "learned.1773053751580",
    "utterance": "🫠",
    "response": "Mokkda wela thiyenne"
  },
  {
    "intent": "learned.1773053776215",
    "utterance": "Hi",
    "response": "හායි нαzυ  සූටි බබෝ..😍❤️\nයාලුවො α∂∂ කරල ¢нαт කරන්නකෝ 😘🎗️"
  },
  {
    "intent": "learned.1773053779494",
    "utterance": "Hi ayye, good to see you!",
    "response": "හායි ishi grl සූටි බබෝ..😍❤️\nයාලුවො α∂∂ කරල ¢нαт කරන්නකෝ 😘🎗️"
  }
]